ghscraper_maru/__init__.py
ghscraper_maru/ghscraper.py
ghscraper_maru-3.0.0.dist-info/LICENSE
ghscraper_maru-3.0.0.dist-info/METADATA
ghscraper_maru-3.0.0.dist-info/WHEEL
ghscraper_maru-3.0.0.dist-info/entry_points.txt
ghscraper_maru-3.0.0.dist-info/RECORD
