Metadata-Version: 2.1
Name: ghscraper_maru
Version: 3.0.0
Summary: A github scraper that finds emails and makes a copy of all of someones repos for searching purposes
Home-page: https://www.github.com/marufromhell/ghscraper
License: GPL-3.0-or-later
Author: maru
Author-email: maru@lithium-dev.xyz
Classifier: License :: OSI Approved :: GNU General Public License v3 or later (GPLv3+)
Classifier: Programming Language :: Python :: 2
Classifier: Programming Language :: Python :: 2.7
Classifier: Programming Language :: Python :: 3
Classifier: Programming Language :: Python :: 3.4
Classifier: Programming Language :: Python :: 3.5
Classifier: Programming Language :: Python :: 3.6
Classifier: Programming Language :: Python :: 3.7
Classifier: Programming Language :: Python :: 3.8
Classifier: Programming Language :: Python :: 3.9
Classifier: Programming Language :: Python :: 3.10
Classifier: Programming Language :: Python :: 3.11
Classifier: Programming Language :: Python :: 3.12
Classifier: Programming Language :: Python :: 3.13
Requires-Dist: click
Requires-Dist: requests
Project-URL: Repository, https://www.github.com/marufromhell/ghscraper
